[
  {
    "title":"AS PORT",
    "date":"2021/9/20~2019/7",
    "discription":"Vue.jsを勉強して何か一つ公開できるものを作りたいと思い作成した。読みやすいように情報の整頓に気を付けた。",
    "tools":["HTML","gulp","Vue.js","vuetify","vue-router"],
    "url":"https://github.com/AS-box/vuePortfolio/wiki"
  },
  {
    "title":"vue.jsでブログを作ってみた(制作途中)",
    "date":"2021/9/20~2019/7",
    "discription":"初めてのVue.jsの勉強にブログ投稿システムを作ろうとしたが、サーバー側の知識が足りず挫折中。expressの勉強をしたので、その知識を生かして再始動する予定。",
    "tools":["HTML","SCSS","gulp","Vue.js","vuex","vue-router"],
    "url":"https://github.com/AS-box/blog-vue/wiki/"
  }
]
